README.md
setup.cfg
setup.py
SatZoomer.egg-info/PKG-INFO
SatZoomer.egg-info/SOURCES.txt
SatZoomer.egg-info/dependency_links.txt
SatZoomer.egg-info/requires.txt
SatZoomer.egg-info/top_level.txt
satzoomer/__init__.py
satzoomer/ghana_tile.py
satzoomer/guyana_tile.py
satzoomer/spectral_indices.py
satzoomer/super_tile.py
satzoomer/utils.py