Metadata-Version: 1.2
Name: SatZoomer
Version: 1.0.0
Summary: Satellite Image Processing
Home-page: https://github.com/JRainbowOS/satzoomer
Author: Jacob Rainbow
Author-email: jacob.rainbow@os.uk
License: UNKNOWN
Platform: UNKNOWN
Classifier: Development Status :: 2 - Pre-Alpha
Classifier: License :: Other/Proprietary License
Classifier: Programming Language :: Python :: 3
Classifier: Operating System :: Microsoft :: Windows
Classifier: Topic :: Scientific/Engineering :: Visualization
Requires-Python: >3.6
